MANIFEST.in
build.sh
build_source.sh
clean.sh
setup.py
agent2/__init__.py
agent2/dojo_util.py
agent2/forms.py
agent2/methods.py
agent2/models.py
agent2/plugin.py
agent2/tests.py
agent2/urls.py
agent2/views.py
agent2/management/__init__.py
agent2/management/commands/__init__.py
agent2/management/commands/pushrecords.py
agent2/templates/agent2/base.html
agent2/templates/agent2/index.html
agent2/templates/agent2/setup.html
openproximity_agent2.egg-info/PKG-INFO
openproximity_agent2.egg-info/SOURCES.txt
openproximity_agent2.egg-info/dependency_links.txt
openproximity_agent2.egg-info/top_level.txt