Metadata-Version: 1.0
Name: openproximity-agent2
Version: 0.0.1
Summary: A data collector that pushes records into a centralized server.
Home-page: https://github.com/OpenProximity/plugins-agent2
Author: Naranjo Manuel Francisco
Author-email: manuel@aircable.net
License: GPL2
Platform: UNKNOWN
